openevals/__init__.py
openevals/exact.py
openevals/llm.py
openevals/py.typed
openevals/types.py
openevals/utils.py
openevals/code/__init__.py
openevals/code/base.py
openevals/code/llm.py
openevals/code/mypy.py
openevals/code/pyright.py
openevals/code/e2b/__init__.py
openevals/code/e2b/execution.py
openevals/code/e2b/pyright.py
openevals/code/e2b/sandbox/files.py
openevals/json/__init__.py
openevals/json/match.py
openevals/prompts/__init__.py
openevals/prompts/code_correctness.py
openevals/prompts/conciseness.py
openevals/prompts/correctness.py
openevals/prompts/hallucination.py
openevals/prompts/rag_groundedness.py
openevals/prompts/rag_helpfulness.py
openevals/prompts/rag_retrieval_relevance.py
openevals/simulators/__init__.py
openevals/simulators/multiturn.py
openevals/simulators/prebuilts.py
openevals/string/__init__.py
openevals/string/embedding_similarity.py
openevals/string/levenshtein.py
openevals-0.0.20.dist-info/licenses/LICENSE
openevals-0.0.20.dist-info/METADATA
openevals-0.0.20.dist-info/WHEEL
openevals-0.0.20.dist-info/top_level.txt
openevals-0.0.20.dist-info/RECORD
