Metadata-Version: 2.4
Name: openevals
Version: 0.0.20
Summary: Open-source evaluators for LLM applications
License: MIT
Requires-Python: >=3.9
License-File: LICENSE
Requires-Dist: langchain>=0.3.18
Requires-Dist: langchain-openai>=0.3.6
Requires-Dist: langsmith>=0.3.32
Requires-Dist: rich>=13.9.4
Provides-Extra: e2b-code-interpreter
Requires-Dist: e2b-code-interpreter>=1.1.1; extra == "e2b-code-interpreter"
Dynamic: license-file
